feruca-0.1.1.dist-info/METADATA
feruca-0.1.1.dist-info/WHEEL
feruca-0.1.1.dist-info/licenses/LICENSE
feruca/__init__.py
feruca/feruca.cpython-312-arm-linux-gnueabihf.so
feruca-0.1.1.dist-info/RECORD
