Metadata-Version: 2.4
Name: feruca
Version: 0.1.1
Classifier: Programming Language :: Rust
Classifier: Programming Language :: Python :: Implementation :: CPython
Classifier: Programming Language :: Python :: Implementation :: PyPy
License-File: LICENSE
Summary: Python bindings for feruca, a Rust implementation of the Unicode Collation Algorithm
Author-email: Theodore Beers <theo.beers@drexel.edu>
License: MIT
Requires-Python: >=3.10
Project-URL: Repository, https://github.com/theodore-s-beers/feruca-py
